LICENCE
README.md
setup.py
ICityRunner/ConvertOutput.py
ICityRunner/FindNeighborhood.py
ICityRunner/GetIcityForBLASTHits.py
ICityRunner/HashSeedExtract.py
ICityRunner/ICityRunner.py
ICityRunner/MakeProfiles.py
ICityRunner/RemoveFASTAIDRedundency.py
ICityRunner/RunPSIBLAST.py
ICityRunner/SortBLASTHitsInMemory.py
ICityRunner/SortRelevance.py
ICityRunner/config.py
ICityRunner.egg-info/PKG-INFO
ICityRunner.egg-info/SOURCES.txt
ICityRunner.egg-info/dependency_links.txt
ICityRunner.egg-info/requires.txt
ICityRunner.egg-info/top_level.txt